setup.py
display/__init__.py
display/arch/windows/display.c
display_package_test.egg-info/PKG-INFO
display_package_test.egg-info/SOURCES.txt
display_package_test.egg-info/dependency_links.txt
display_package_test.egg-info/top_level.txt