Metadata-Version: 2.1
Name: display-package-test
Version: 1.0
Summary: Display Package
Home-page: UNKNOWN
License: UNKNOWN
Platform: UNKNOWN
